long_range_models/__init__.py
long_range_models/lru.py
long_range_models/s4.py
long_range_models/s5.py
long_range_models/sequence_models.py
long_range_models/ssm.py
long_range_models/types.py
long_range_models-0.0.1.dist-info/LICENSE
long_range_models-0.0.1.dist-info/METADATA
long_range_models-0.0.1.dist-info/WHEEL
long_range_models-0.0.1.dist-info/top_level.txt
long_range_models-0.0.1.dist-info/RECORD
