Metadata-Version: 2.1
Name: long-range-models
Version: 0.0.1
Summary: Simple Flax implementations of long-range sequence models
Home-page: https://github.com/gbrlfaria/long_range_models
Author: Gabriel Faria
Author-email: gabfaria.cs@gmail.com
Keywords: artificial intelligence,state space models,long range models
Classifier: Development Status :: 3 - Alpha
Classifier: Intended Audience :: Developers
Classifier: Intended Audience :: Science/Research
Classifier: License :: OSI Approved :: MIT License
Classifier: Programming Language :: Python :: 3.11
Classifier: Topic :: Scientific/Engineering :: Artificial Intelligence
License-File: LICENSE
Requires-Dist: jax >=0.4.14
Requires-Dist: flax >=0.7.3
Provides-Extra: examples
Requires-Dist: clu >=0.0.9 ; extra == 'examples'
Requires-Dist: optax >=0.1.7 ; extra == 'examples'
Requires-Dist: tensorflow >=2.13.0 ; extra == 'examples'
Requires-Dist: tensorflow-datasets >=4.9.3 ; extra == 'examples'
